zoomto/__init__.py
zoomto/app.py
zoomto/autogui.py
zoomto/cfg.py
zoomto/overload.py
zoomto/proc.py
zoomto/static/build/asset-manifest.json
zoomto/static/build/favicon.ico
zoomto/static/build/index.html
zoomto/static/build/logo192.png
zoomto/static/build/logo512.png
zoomto/static/build/manifest.json
zoomto/static/build/robots.txt
zoomto/static/build/static/css/main.e6c13ad2.css
zoomto/static/build/static/css/main.e6c13ad2.css.map
zoomto/static/build/static/js/453.9d3adcdd.chunk.js
zoomto/static/build/static/js/453.9d3adcdd.chunk.js.map
zoomto/static/build/static/js/main.eb11e087.js
zoomto/static/build/static/js/main.eb11e087.js.LICENSE.txt
zoomto/static/build/static/js/main.eb11e087.js.map
zoomto/static/default-video-thumbnail.jpg
zoomto/static/meeting_expand.png
zoomto/static/sharevid.png
zoomto/utils.py
zoomto/videoIndex.py
zoomto-0.9.1.dist-info/entry_points.txt
zoomto-0.9.1.dist-info/LICENSE
zoomto-0.9.1.dist-info/METADATA
zoomto-0.9.1.dist-info/WHEEL
zoomto-0.9.1.dist-info/RECORD
